autoSnake/___init___.py
autoSnake/game.py
autosnake-0.1.3.dist-info/METADATA
autosnake-0.1.3.dist-info/WHEEL
autosnake-0.1.3.dist-info/entry_points.txt
autosnake-0.1.3.dist-info/top_level.txt
autosnake-0.1.3.dist-info/RECORD
