Metadata-Version: 2.4
Name: autosnake
Version: 0.1.3
Summary: Automatic Snake Game using Turtle and BFS
Author-email: Your_Name <Your_Email@example.com>
License: MIT
Requires-Python: >=3.7
